qexpy/__init__.py
qexpy/data/__init__.py
qexpy/data/data.py
qexpy/data/datasets.py
qexpy/data/operations.py
qexpy/data/utils.py
qexpy/fitting/__init__.py
qexpy/fitting/fitting.py
qexpy/fitting/utils.py
qexpy/plotting/__init__.py
qexpy/plotting/plotobjects.py
qexpy/plotting/plotting.py
qexpy/settings/__init__.py
qexpy/settings/literals.py
qexpy/settings/settings.py
qexpy/utils/__init__.py
qexpy/utils/exceptions.py
qexpy/utils/printing.py
qexpy/utils/units.py
qexpy/utils/utils.py
qexpy-2.0.4.dist-info/licenses/LICENSE
qexpy-2.0.4.dist-info/METADATA
qexpy-2.0.4.dist-info/WHEEL
qexpy-2.0.4.dist-info/top_level.txt
qexpy-2.0.4.dist-info/RECORD
